Metadata-Version: 1.1
Name: spider80s
Version: 0.0.2
Summary: 80s电影爬虫 输出给定电影/电视剧的迅雷下载地址
Home-page: https://github.com/vcancy/spider80s
Author: vcancy
Author-email: happiness1019@gmail.com
License: MIT
Keywords: 80s  spider movies
Platform: UNKNOWN
Classifier: License :: OSI Approved :: MIT License
Classifier: Programming Language :: Python
Classifier: Intended Audience :: Developers
Classifier: Operating System :: OS Independent
